sensevoice/sense_voice.py
sensevoice/onnx/fsmn_vad_ort_session.py
sensevoice/onnx/sense_voice_ort_session.py
sensevoice/utils/frontend.py
sensevoice/utils/fsmn_vad.py
sensevoice_onnx-1.1.0.dist-info/METADATA
sensevoice_onnx-1.1.0.dist-info/WHEEL
sensevoice_onnx-1.1.0.dist-info/entry_points.txt
sensevoice_onnx-1.1.0.dist-info/top_level.txt
sensevoice_onnx-1.1.0.dist-info/RECORD
