Metadata-Version: 2.1
Name: sensevoice-onnx
Version: 1.1.0
Summary: SenseVoice-python: A enterprise-grade open source multi-language asr system from funasr opensource with onnxruntime
Home-page: https://github.com/lovemefan/SenseVoice-python
Author: Lovemefan
Author-email: lovemefan@outlook.com
License: The MIT License
Platform: UNKNOWN
Classifier: Programming Language :: Python
Classifier: Programming Language :: Python :: 3
Classifier: Programming Language :: Python :: 3.8
Classifier: Programming Language :: Python :: 3.9
Classifier: Programming Language :: Python :: 3.10
Classifier: Programming Language :: Python :: 3.11
Classifier: Development Status :: 5 - Production/Stable
Classifier: Intended Audience :: Science/Research
Classifier: Operating System :: POSIX :: Linux
Classifier: License :: OSI Approved :: MIT License
Classifier: Topic :: Multimedia :: Sound/Audio :: Speech
Classifier: Topic :: Scientific/Engineering :: Artificial Intelligence
Classifier: Topic :: Software Development :: Libraries :: Python Modules
Requires-Python: >=3.8.0
Requires-Dist: setuptools<=65.0
Requires-Dist: numpy==1.24.4
Requires-Dist: kaldi-native-fbank
Requires-Dist: onnxruntime==1.18.0
Requires-Dist: sentencepiece==0.2.0
Requires-Dist: soundfile==0.12.1
Requires-Dist: huggingface-hub
